[
  {
    "studyLevel": "PHD",
    "specification": "Software Engineering",
    "universityIndex": 0,
    "description": "pla pla pla",
    "startAge": 24,
    "endAge": 35,
    "perfectAge": 26,
    "englishLevel": "C1",
    "startAverage": 75,
    "academicLanguage": "English",
    "agePercentage": 30,
    "averagePercentage":  40,
    "englishLevelPercentage": 30,
    "fundation" : "Semi funded"
  },
  {
    "studyLevel": "PHD",
    "specification": "Medicine",
    "universityIndex": 0,
    "description": "pla pla pla",
    "startAge": 24,
    "endAge": 35,
    "perfectAge": 26,
    "englishLevel": "C1",
    "startAverage": 75,
    "academicLanguage": "English",
    "agePercentage": 30,
    "averagePercentage":  40,
    "englishLevelPercentage": 30,
    "fundation" : "Fully funded"
  },
  {
  "studyLevel": "Master",
  "specification": "Pharmacy",
  "universityIndex": 0,
  "description": "mesho mesho mesho",
  "startAge": 24,
  "endAge": 35,
  "perfectAge": 26,
  "englishLevel": "B3",
  "startAverage": 75,
  "academicLanguage": "English",
  "agePercentage": 30,
  "averagePercentage":  40,
  "englishLevelPercentage": 30,
  "fundation" : "Fully funded"
  },
  {
    "studyLevel": "PHD",
    "specification": "Pharmacy",
    "universityIndex": 0,
    "description": "mesho mesho mesho",
    "startAge": 24,
    "endAge": 35,
    "perfectAge": 21,
    "englishLevel": "B3",
    "startAverage": 80,
    "academicLanguage": "English",
    "agePercentage": 30,
    "averagePercentage":  40,
    "englishLevelPercentage": 30,
    "fundation" : "Fully funded"
  },
  {
    "studyLevel": "PHD",
    "specification": "Pharmacy",
    "universityIndex": 0,
    "description": "mesho mesho mesho",
    "startAge": 20,
    "endAge": 30,
    "perfectAge": 30,
    "englishLevel": "A1",
    "startAverage": 50,
    "academicLanguage": "English",
    "agePercentage": 20,
    "averagePercentage":  50,
    "englishLevelPercentage": 30,
    "fundation" : "Fully funded"
  }

]